[{"debug_info": {"running_date": "13/12/23", "running_time": "20:42:25"}, "data": {"coti": [{"name": "D\u00f3lar oficial", "coti": {"Compra": "$773,97", "Venta": "$832,64"}}, {"name": "D\u00f3lar blue", "coti": {"Compra": "$1020,00", "Venta": "$1070,00"}}, {"name": "D\u00f3lar tarjeta", "coti": {"Venta": "$1332,22"}}, {"name": "D\u00f3lar turista", "coti": {"Venta": "$1332,22"}}, {"name": "D\u00f3lar MEP", "coti": {"Venta": "$1015,11"}}, {"name": "D\u00f3lar CCL", "coti": {"Venta": "$1012,36"}}, {"name": "D\u00f3lar mayorista", "coti": {"Venta": "$799,95"}}, {"name": "Euro", "coti": {"Compra": "$842,24", "Venta": "$905,83"}}]}}, {"debug_info": {"running_date": "13/12/23", "running_time": "21:00:03"}, "data": {"coti": [{"name": "D\u00f3lar oficial", "coti": {"Compra": "$773,97", "Venta": "$832,64"}}, {"name": "D\u00f3lar blue", "coti": {"Compra": "$1020,00", "Venta": "$1070,00"}}, {"name": "D\u00f3lar tarjeta", "coti": {"Venta": "$1332,22"}}, {"name": "D\u00f3lar turista", "coti": {"Venta": "$1332,22"}}, {"name": "D\u00f3lar MEP", "coti": {"Venta": "$1015,11"}}, {"name": "D\u00f3lar CCL", "coti": {"Venta": "$1012,36"}}, {"name": "D\u00f3lar mayorista", "coti": {"Venta": "$799,95"}}, {"name": "Euro", "coti": {"Compra": "$842,24", "Venta": "$905,83"}}]}}, {"debug_info": {"running_date": "13/12/23", "running_time": "21:30:04"}, "data": {"coti": [{"name": "D\u00f3lar oficial", "coti": {"Compra": "$773,97", "Venta": "$832,64"}}, {"name": "D\u00f3lar blue", "coti": {"Compra": "$1020,00", "Venta": "$1070,00"}}, {"name": "D\u00f3lar tarjeta", "coti": {"Venta": "$1332,22"}}, {"name": "D\u00f3lar turista", "coti": {"Venta": "$1332,22"}}, {"name": "D\u00f3lar MEP", "coti": {"Venta": "$1015,11"}}, {"name": "D\u00f3lar CCL", "coti": {"Venta": "$1012,36"}}, {"name": "D\u00f3lar mayorista", "coti": {"Venta": "$799,95"}}, {"name": "Euro", "coti": {"Compra": "$842,24", "Venta": "$905,83"}}]}}, {"debug_info": {"running_date": "13/12/23", "running_time": "22:00:04"}, "data": {"coti": [{"name": "D\u00f3lar oficial", "coti": {"Compra": "$773,97", "Venta": "$832,64"}}, {"name": "D\u00f3lar blue", "coti": {"Compra": "$1020,00", "Venta": "$1070,00"}}, {"name": "D\u00f3lar tarjeta", "coti": {"Venta": "$1332,22"}}, {"name": "D\u00f3lar turista", "coti": {"Venta": "$1332,22"}}, {"name": "D\u00f3lar MEP", "coti": {"Venta": "$1015,11"}}, {"name": "D\u00f3lar CCL", "coti": {"Venta": "$1012,36"}}, {"name": "D\u00f3lar mayorista", "coti": {"Venta": "$799,95"}}, {"name": "Euro", "coti": {"Compra": "$842,24", "Venta": "$905,83"}}]}}, {"debug_info": {"running_date": "13/12/23", "running_time": "22:30:04"}, "data": {"coti": [{"name": "D\u00f3lar oficial", "coti": {"Compra": "$773,97", "Venta": "$832,64"}}, {"name": "D\u00f3lar blue", "coti": {"Compra": "$1020,00", "Venta": "$1070,00"}}, {"name": "D\u00f3lar tarjeta", "coti": {"Venta": "$1332,22"}}, {"name": "D\u00f3lar turista", "coti": {"Venta": "$1332,22"}}, {"name": "D\u00f3lar MEP", "coti": {"Venta": "$1015,11"}}, {"name": "D\u00f3lar CCL", "coti": {"Venta": "$1012,36"}}, {"name": "D\u00f3lar mayorista", "coti": {"Venta": "$799,95"}}, {"name": "Euro", "coti": {"Compra": "$842,24", "Venta": "$905,83"}}]}}, {"debug_info": {"running_date": "13/12/23", "running_time": "23:00:04"}, "data": {"coti": [{"name": "D\u00f3lar oficial", "coti": {"Compra": "$773,97", "Venta": "$832,64"}}, {"name": "D\u00f3lar blue", "coti": {"Compra": "$1020,00", "Venta": "$1070,00"}}, {"name": "D\u00f3lar tarjeta", "coti": {"Venta": "$1332,22"}}, {"name": "D\u00f3lar turista", "coti": {"Venta": "$1332,22"}}, {"name": "D\u00f3lar MEP", "coti": {"Venta": "$1015,11"}}, {"name": "D\u00f3lar CCL", "coti": {"Venta": "$1012,36"}}, {"name": "D\u00f3lar mayorista", "coti": {"Venta": "$799,95"}}, {"name": "Euro", "coti": {"Compra": "$842,24", "Venta": "$905,83"}}]}}, {"debug_info": {"running_date": "14/12/23", "running_time": "09:28:29"}, "data": {"coti": [{"name": "D\u00f3lar oficial", "coti": {"Compra": "$773,97", "Venta": "$832,64"}}, {"name": "D\u00f3lar blue", "coti": {"Compra": "$1040,00", "Venta": "$1070,00"}}, {"name": "D\u00f3lar tarjeta", "coti": {"Venta": "$1332,22"}}, {"name": "D\u00f3lar turista", "coti": {"Venta": "$1332,22"}}, {"name": "D\u00f3lar MEP", "coti": {"Venta": "$1037,29"}}, {"name": "D\u00f3lar CCL", "coti": {"Venta": "$1009,01"}}, {"name": "D\u00f3lar mayorista", "coti": {"Venta": "$366,50"}}, {"name": "Euro", "coti": {"Compra": "$842,24", "Venta": "$905,83"}}]}}, {"debug_info": {"running_date": "14/12/23", "running_time": "09:30:12"}, "data": {"coti": [{"name": "D\u00f3lar oficial", "coti": {"Compra": "$773,97", "Venta": "$832,64"}}, {"name": "D\u00f3lar blue", "coti": {"Compra": "$1040,00", "Venta": "$1070,00"}}, {"name": "D\u00f3lar tarjeta", "coti": {"Venta": "$1332,22"}}, {"name": "D\u00f3lar turista", "coti": {"Venta": "$1332,22"}}, {"name": "D\u00f3lar MEP", "coti": {"Venta": "$1037,29"}}, {"name": "D\u00f3lar CCL", "coti": {"Venta": "$1009,01"}}, {"name": "D\u00f3lar mayorista", "coti": {"Venta": "$366,50"}}, {"name": "Euro", "coti": {"Compra": "$842,24", "Venta": "$905,83"}}]}}, {"debug_info": {"running_date": "14/12/23", "running_time": "10:00:03"}, "data": {"coti": [{"name": "D\u00f3lar oficial", "coti": {"Compra": "$773,97", "Venta": "$832,64"}}, {"name": "D\u00f3lar blue", "coti": {"Compra": "$1040,00", "Venta": "$1070,00"}}, {"name": "D\u00f3lar tarjeta", "coti": {"Venta": "$1332,22"}}, {"name": "D\u00f3lar turista", "coti": {"Venta": "$1332,22"}}, {"name": "D\u00f3lar MEP", "coti": {"Venta": "$1037,29"}}, {"name": "D\u00f3lar CCL", "coti": {"Venta": "$1009,01"}}, {"name": "D\u00f3lar mayorista", "coti": {"Venta": "$366,50"}}, {"name": "Euro", "coti": {"Compra": "$842,24", "Venta": "$905,83"}}]}}, {"debug_info": {"running_date": "14/12/23", "running_time": "10:30:04"}, "data": {"coti": [{"name": "D\u00f3lar oficial", "coti": {"Compra": "$773,97", "Venta": "$832,64"}}, {"name": "D\u00f3lar blue", "coti": {"Compra": "$1040,00", "Venta": "$1070,00"}}, {"name": "D\u00f3lar tarjeta", "coti": {"Venta": "$1332,22"}}, {"name": "D\u00f3lar turista", "coti": {"Venta": "$1332,22"}}, {"name": "D\u00f3lar MEP", "coti": {"Venta": "$1037,29"}}, {"name": "D\u00f3lar CCL", "coti": {"Venta": "$1009,01"}}, {"name": "D\u00f3lar mayorista", "coti": {"Venta": "$366,50"}}, {"name": "Euro", "coti": {"Compra": "$842,24", "Venta": "$905,83"}}]}}, {"debug_info": {"running_date": "14/12/23", "running_time": "11:00:02"}, "data": {"coti": [{"name": "D\u00f3lar oficial", "coti": {"Compra": "$773,97", "Venta": "$832,64"}}, {"name": "D\u00f3lar blue", "coti": {"Compra": "$1020,00", "Venta": "$1070,00"}}, {"name": "D\u00f3lar tarjeta", "coti": {"Venta": "$1332,22"}}, {"name": "D\u00f3lar turista", "coti": {"Venta": "$1332,22"}}, {"name": "D\u00f3lar MEP", "coti": {"Venta": "$1037,29"}}, {"name": "D\u00f3lar CCL", "coti": {"Venta": "$1008,76"}}, {"name": "D\u00f3lar mayorista", "coti": {"Venta": "$366,50"}}, {"name": "Euro", "coti": {"Compra": "$842,24", "Venta": "$905,83"}}]}}, {"debug_info": {"running_date": "14/12/23", "running_time": "11:30:03"}, "data": {"coti": [{"name": "D\u00f3lar oficial", "coti": {"Compra": "$773,97", "Venta": "$832,64"}}, {"name": "D\u00f3lar blue", "coti": {"Compra": "$1020,00", "Venta": "$1070,00"}}, {"name": "D\u00f3lar tarjeta", "coti": {"Venta": "$1332,22"}}, {"name": "D\u00f3lar turista", "coti": {"Venta": "$1332,22"}}, {"name": "D\u00f3lar MEP", "coti": {"Venta": "$1037,29"}}, {"name": "D\u00f3lar CCL", "coti": {"Venta": "$1002,00"}}, {"name": "D\u00f3lar mayorista", "coti": {"Venta": "$366,50"}}, {"name": "Euro", "coti": {"Compra": "$842,24", "Venta": "$905,83"}}]}}, {"debug_info": {"running_date": "14/12/23", "running_time": "12:00:03"}, "data": {"coti": [{"name": "D\u00f3lar oficial", "coti": {"Compra": "$776,81", "Venta": "$836,44"}}, {"name": "D\u00f3lar blue", "coti": {"Compra": "$980,00", "Venta": "$1030,00"}}, {"name": "D\u00f3lar tarjeta", "coti": {"Venta": "$1338,3"}}, {"name": "D\u00f3lar turista", "coti": {"Venta": "$1338,3"}}, {"name": "D\u00f3lar MEP", "coti": {"Venta": "$1015,45"}}, {"name": "D\u00f3lar CCL", "coti": {"Venta": "$996,89"}}, {"name": "D\u00f3lar mayorista", "coti": {"Venta": "$366,50"}}, {"name": "Euro", "coti": {"Compra": "$842,24", "Venta": "$905,83"}}]}}, {"debug_info": {"running_date": "14/12/23", "running_time": "12:30:02"}, "data": {"coti": [{"name": "D\u00f3lar oficial", "coti": {"Compra": "$776,81", "Venta": "$836,44"}}, {"name": "D\u00f3lar blue", "coti": {"Compra": "$980,00", "Venta": "$1030,00"}}, {"name": "D\u00f3lar tarjeta", "coti": {"Venta": "$1338,3"}}, {"name": "D\u00f3lar turista", "coti": {"Venta": "$1338,3"}}, {"name": "D\u00f3lar MEP", "coti": {"Venta": "$1015,45"}}, {"name": "D\u00f3lar CCL", "coti": {"Venta": "$991,18"}}, {"name": "D\u00f3lar mayorista", "coti": {"Venta": "$366,50"}}, {"name": "Euro", "coti": {"Compra": "$842,24", "Venta": "$905,83"}}]}}, {"debug_info": {"running_date": "14/12/23", "running_time": "13:00:02"}, "data": {"coti": [{"name": "D\u00f3lar oficial", "coti": {"Compra": "$776,81", "Venta": "$836,44"}}, {"name": "D\u00f3lar blue", "coti": {"Compra": "$945,00", "Venta": "$995,00"}}, {"name": "D\u00f3lar tarjeta", "coti": {"Venta": "$1338,3"}}, {"name": "D\u00f3lar turista", "coti": {"Venta": "$1338,3"}}, {"name": "D\u00f3lar MEP", "coti": {"Venta": "$1026,19"}}, {"name": "D\u00f3lar CCL", "coti": {"Venta": "$992,80"}}, {"name": "D\u00f3lar mayorista", "coti": {"Venta": "$366,50"}}, {"name": "Euro", "coti": {"Compra": "$842,24", "Venta": "$905,83"}}]}}, {"debug_info": {"running_date": "14/12/23", "running_time": "20:30:09"}, "data": {"coti": [{"name": "D\u00f3lar oficial", "coti": {"Compra": "$778,24", "Venta": "$837,91"}}, {"name": "D\u00f3lar blue", "coti": {"Compra": "$940,00", "Venta": "$990,00"}}, {"name": "D\u00f3lar tarjeta", "coti": {"Venta": "$1340,66"}}, {"name": "D\u00f3lar turista", "coti": {"Venta": "$1340,66"}}, {"name": "D\u00f3lar MEP", "coti": {"Venta": "$1010,01"}}, {"name": "D\u00f3lar CCL", "coti": {"Venta": "$1017,08"}}, {"name": "D\u00f3lar mayorista", "coti": {"Venta": "$800,50"}}, {"name": "Euro", "coti": {"Compra": "$845,81", "Venta": "$915,76"}}]}}, {"debug_info": {"running_date": "14/12/23", "running_time": "21:00:03"}, "data": {"coti": [{"name": "D\u00f3lar oficial", "coti": {"Compra": "$778,24", "Venta": "$837,91"}}, {"name": "D\u00f3lar blue", "coti": {"Compra": "$940,00", "Venta": "$990,00"}}, {"name": "D\u00f3lar tarjeta", "coti": {"Venta": "$1340,66"}}, {"name": "D\u00f3lar turista", "coti": {"Venta": "$1340,66"}}, {"name": "D\u00f3lar MEP", "coti": {"Venta": "$1010,01"}}, {"name": "D\u00f3lar CCL", "coti": {"Venta": "$1017,08"}}, {"name": "D\u00f3lar mayorista", "coti": {"Venta": "$800,50"}}, {"name": "Euro", "coti": {"Compra": "$845,81", "Venta": "$915,76"}}]}}, {"debug_info": {"running_date": "14/12/23", "running_time": "21:30:03"}, "data": {"coti": [{"name": "D\u00f3lar oficial", "coti": {"Compra": "$778,24", "Venta": "$837,91"}}, {"name": "D\u00f3lar blue", "coti": {"Compra": "$940,00", "Venta": "$990,00"}}, {"name": "D\u00f3lar tarjeta", "coti": {"Venta": "$1340,66"}}, {"name": "D\u00f3lar turista", "coti": {"Venta": "$1340,66"}}, {"name": "D\u00f3lar MEP", "coti": {"Venta": "$1010,01"}}, {"name": "D\u00f3lar CCL", "coti": {"Venta": "$1017,08"}}, {"name": "D\u00f3lar mayorista", "coti": {"Venta": "$800,50"}}, {"name": "Euro", "coti": {"Compra": "$845,81", "Venta": "$915,76"}}]}}, {"debug_info": {"running_date": "14/12/23", "running_time": "22:00:04"}, "data": {"coti": [{"name": "D\u00f3lar oficial", "coti": {"Compra": "$778,24", "Venta": "$837,91"}}, {"name": "D\u00f3lar blue", "coti": {"Compra": "$940,00", "Venta": "$990,00"}}, {"name": "D\u00f3lar tarjeta", "coti": {"Venta": "$1340,66"}}, {"name": "D\u00f3lar turista", "coti": {"Venta": "$1340,66"}}, {"name": "D\u00f3lar MEP", "coti": {"Venta": "$1010,01"}}, {"name": "D\u00f3lar CCL", "coti": {"Venta": "$1017,08"}}, {"name": "D\u00f3lar mayorista", "coti": {"Venta": "$800,50"}}, {"name": "Euro", "coti": {"Compra": "$845,81", "Venta": "$915,76"}}]}}, {"debug_info": {"running_date": "14/12/23", "running_time": "22:30:05"}, "data": {"coti": [{"name": "D\u00f3lar oficial", "coti": {"Compra": "$778,24", "Venta": "$837,91"}}, {"name": "D\u00f3lar blue", "coti": {"Compra": "$940,00", "Venta": "$990,00"}}, {"name": "D\u00f3lar tarjeta", "coti": {"Venta": "$1340,66"}}, {"name": "D\u00f3lar turista", "coti": {"Venta": "$1340,66"}}, {"name": "D\u00f3lar MEP", "coti": {"Venta": "$1010,01"}}, {"name": "D\u00f3lar CCL", "coti": {"Venta": "$1017,08"}}, {"name": "D\u00f3lar mayorista", "coti": {"Venta": "$800,50"}}, {"name": "Euro", "coti": {"Compra": "$845,81", "Venta": "$915,76"}}]}}, {"debug_info": {"running_date": "14/12/23", "running_time": "23:00:04"}, "data": {"coti": [{"name": "D\u00f3lar oficial", "coti": {"Compra": "$778,24", "Venta": "$837,91"}}, {"name": "D\u00f3lar blue", "coti": {"Compra": "$940,00", "Venta": "$990,00"}}, {"name": "D\u00f3lar tarjeta", "coti": {"Venta": "$1340,66"}}, {"name": "D\u00f3lar turista", "coti": {"Venta": "$1340,66"}}, {"name": "D\u00f3lar MEP", "coti": {"Venta": "$1010,01"}}, {"name": "D\u00f3lar CCL", "coti": {"Venta": "$1017,08"}}, {"name": "D\u00f3lar mayorista", "coti": {"Venta": "$800,50"}}, {"name": "Euro", "coti": {"Compra": "$845,81", "Venta": "$915,76"}}]}}, {"debug_info": {"running_date": "15/12/23", "running_time": "08:30:04"}, "data": {"coti": [{"name": "D\u00f3lar oficial", "coti": {"Compra": "$778,24", "Venta": "$837,91"}}, {"name": "D\u00f3lar blue", "coti": {"Compra": "$940,00", "Venta": "$990,00"}}, {"name": "D\u00f3lar tarjeta", "coti": {"Venta": "$1340,66"}}, {"name": "D\u00f3lar turista", "coti": {"Venta": "$1340,66"}}, {"name": "D\u00f3lar MEP", "coti": {"Venta": "$1010,01"}}, {"name": "D\u00f3lar CCL", "coti": {"Venta": "$1017,08"}}, {"name": "D\u00f3lar mayorista", "coti": {"Venta": "$800,50"}}, {"name": "Euro", "coti": {"Compra": "$845,81", "Venta": "$915,76"}}]}}, {"debug_info": {"running_date": "15/12/23", "running_time": "09:00:04"}, "data": {"coti": [{"name": "D\u00f3lar oficial", "coti": {"Compra": "$778,24", "Venta": "$837,91"}}, {"name": "D\u00f3lar blue", "coti": {"Compra": "$940,00", "Venta": "$990,00"}}, {"name": "D\u00f3lar tarjeta", "coti": {"Venta": "$1340,66"}}, {"name": "D\u00f3lar turista", "coti": {"Venta": "$1340,66"}}, {"name": "D\u00f3lar MEP", "coti": {"Venta": "$1010,01"}}, {"name": "D\u00f3lar CCL", "coti": {"Venta": "$1017,08"}}, {"name": "D\u00f3lar mayorista", "coti": {"Venta": "$800,50"}}, {"name": "Euro", "coti": {"Compra": "$845,81", "Venta": "$915,76"}}]}}, {"debug_info": {"running_date": "15/12/23", "running_time": "09:30:05"}, "data": {"coti": [{"name": "D\u00f3lar oficial", "coti": {"Compra": "$778,24", "Venta": "$837,91"}}, {"name": "D\u00f3lar blue", "coti": {"Compra": "$960,00", "Venta": "$990,00"}}, {"name": "D\u00f3lar tarjeta", "coti": {"Venta": "$1340,66"}}, {"name": "D\u00f3lar turista", "coti": {"Venta": "$1340,66"}}, {"name": "D\u00f3lar MEP", "coti": {"Venta": "$1003,94"}}, {"name": "D\u00f3lar CCL", "coti": {"Venta": "$1014,73"}}, {"name": "D\u00f3lar mayorista", "coti": {"Venta": "$799,98"}}, {"name": "Euro", "coti": {"Compra": "$845,81", "Venta": "$915,76"}}]}}, {"debug_info": {"running_date": "15/12/23", "running_time": "10:00:08"}, "data": {"coti": [{"name": "D\u00f3lar oficial", "coti": {"Compra": "$778,24", "Venta": "$837,91"}}, {"name": "D\u00f3lar blue", "coti": {"Compra": "$960,00", "Venta": "$990,00"}}, {"name": "D\u00f3lar tarjeta", "coti": {"Venta": "$1340,66"}}, {"name": "D\u00f3lar turista", "coti": {"Venta": "$1340,66"}}, {"name": "D\u00f3lar MEP", "coti": {"Venta": "$1003,94"}}, {"name": "D\u00f3lar CCL", "coti": {"Venta": "$1014,73"}}, {"name": "D\u00f3lar mayorista", "coti": {"Venta": "$799,98"}}, {"name": "Euro", "coti": {"Compra": "$845,81", "Venta": "$915,76"}}]}}, {"debug_info": {"running_date": "15/12/23", "running_time": "10:30:07"}, "data": {"coti": [{"name": "D\u00f3lar oficial", "coti": {"Compra": "$778,24", "Venta": "$837,91"}}, {"name": "D\u00f3lar blue", "coti": {"Compra": "$940,00", "Venta": "$990,00"}}, {"name": "D\u00f3lar tarjeta", "coti": {"Venta": "$1340,66"}}, {"name": "D\u00f3lar turista", "coti": {"Venta": "$1340,66"}}, {"name": "D\u00f3lar MEP", "coti": {"Venta": "$1003,94"}}, {"name": "D\u00f3lar CCL", "coti": {"Venta": "$1014,73"}}, {"name": "D\u00f3lar mayorista", "coti": {"Venta": "$799,98"}}, {"name": "Euro", "coti": {"Compra": "$845,81", "Venta": "$915,76"}}]}}, {"debug_info": {"running_date": "15/12/23", "running_time": "11:00:05"}, "data": {"coti": [{"name": "D\u00f3lar oficial", "coti": {"Compra": "$778,24", "Venta": "$837,91"}}, {"name": "D\u00f3lar blue", "coti": {"Compra": "$940,00", "Venta": "$990,00"}}, {"name": "D\u00f3lar tarjeta", "coti": {"Venta": "$1340,66"}}, {"name": "D\u00f3lar turista", "coti": {"Venta": "$1340,66"}}, {"name": "D\u00f3lar MEP", "coti": {"Venta": "$1003,94"}}, {"name": "D\u00f3lar CCL", "coti": {"Venta": "$1014,91"}}, {"name": "D\u00f3lar mayorista", "coti": {"Venta": "$799,98"}}, {"name": "Euro", "coti": {"Compra": "$845,81", "Venta": "$915,76"}}]}}, {"debug_info": {"running_date": "15/12/23", "running_time": "11:30:04"}, "data": {"coti": [{"name": "D\u00f3lar oficial", "coti": {"Compra": "$778,24", "Venta": "$837,91"}}, {"name": "D\u00f3lar blue", "coti": {"Compra": "$940,00", "Venta": "$990,00"}}, {"name": "D\u00f3lar tarjeta", "coti": {"Venta": "$1340,66"}}, {"name": "D\u00f3lar turista", "coti": {"Venta": "$1340,66"}}, {"name": "D\u00f3lar MEP", "coti": {"Venta": "$1003,94"}}, {"name": "D\u00f3lar CCL", "coti": {"Venta": "$996,99"}}, {"name": "D\u00f3lar mayorista", "coti": {"Venta": "$799,98"}}, {"name": "Euro", "coti": {"Compra": "$845,81", "Venta": "$915,76"}}]}}, {"debug_info": {"running_date": "15/12/23", "running_time": "12:00:23"}, "data": {"coti": [{"name": "D\u00f3lar oficial", "coti": {"Compra": "$782,53", "Venta": "$838,18"}}, {"name": "D\u00f3lar blue", "coti": {"Compra": "$940,00", "Venta": "$990,00"}}, {"name": "D\u00f3lar tarjeta", "coti": {"Venta": "$1341,09"}}, {"name": "D\u00f3lar turista", "coti": {"Venta": "$1341,09"}}, {"name": "D\u00f3lar MEP", "coti": {"Venta": "$996,16"}}, {"name": "D\u00f3lar CCL", "coti": {"Venta": "$992,32"}}, {"name": "D\u00f3lar mayorista", "coti": {"Venta": "$799,98"}}, {"name": "Euro", "coti": {"Compra": "$845,81", "Venta": "$915,76"}}]}}, {"debug_info": {"running_date": "15/12/23", "running_time": "14:30:05"}, "data": {"coti": [{"name": "D\u00f3lar oficial", "coti": {"Compra": "$782,64", "Venta": "$839,48"}}, {"name": "D\u00f3lar blue", "coti": {"Compra": "$920,00", "Venta": "$970,00"}}, {"name": "D\u00f3lar tarjeta", "coti": {"Venta": "$1343,17"}}, {"name": "D\u00f3lar turista", "coti": {"Venta": "$1343,17"}}, {"name": "D\u00f3lar MEP", "coti": {"Venta": "$1012,10"}}, {"name": "D\u00f3lar CCL", "coti": {"Venta": "$1009,58"}}, {"name": "D\u00f3lar mayorista", "coti": {"Venta": "$799,98"}}, {"name": "Euro", "coti": {"Compra": "$856,79", "Venta": "$918,00"}}]}}, {"debug_info": {"running_date": "15/12/23", "running_time": "15:00:07"}, "data": {"coti": [{"name": "D\u00f3lar oficial", "coti": {"Compra": "$782,64", "Venta": "$839,48"}}, {"name": "D\u00f3lar blue", "coti": {"Compra": "$920,00", "Venta": "$970,00"}}, {"name": "D\u00f3lar tarjeta", "coti": {"Venta": "$1343,17"}}, {"name": "D\u00f3lar turista", "coti": {"Venta": "$1343,17"}}, {"name": "D\u00f3lar MEP", "coti": {"Venta": "$1006,00"}}, {"name": "D\u00f3lar CCL", "coti": {"Venta": "$1012,06"}}, {"name": "D\u00f3lar mayorista", "coti": {"Venta": "$799,98"}}, {"name": "Euro", "coti": {"Compra": "$856,79", "Venta": "$918,00"}}]}}, {"debug_info": {"running_date": "15/12/23", "running_time": "15:30:05"}, "data": {"coti": [{"name": "D\u00f3lar oficial", "coti": {"Compra": "$782,64", "Venta": "$839,48"}}, {"name": "D\u00f3lar blue", "coti": {"Compra": "$920,00", "Venta": "$970,00"}}, {"name": "D\u00f3lar tarjeta", "coti": {"Venta": "$1343,17"}}, {"name": "D\u00f3lar turista", "coti": {"Venta": "$1343,17"}}, {"name": "D\u00f3lar MEP", "coti": {"Venta": "$1006,00"}}, {"name": "D\u00f3lar CCL", "coti": {"Venta": "$1011,68"}}, {"name": "D\u00f3lar mayorista", "coti": {"Venta": "$799,98"}}, {"name": "Euro", "coti": {"Compra": "$855,94", "Venta": "$918,90"}}]}}, {"debug_info": {"running_date": "17/12/23", "running_time": "10:30:06"}, "data": {"coti": [{"name": "D\u00f3lar oficial", "coti": {"Compra": "$782,53", "Venta": "$838,18"}}, {"name": "D\u00f3lar blue", "coti": {"Compra": "$920,00", "Venta": "$970,00"}}, {"name": "D\u00f3lar tarjeta", "coti": {"Venta": "$1341,09"}}, {"name": "D\u00f3lar turista", "coti": {"Venta": "$1341,09"}}, {"name": "D\u00f3lar MEP", "coti": {"Venta": "$1000,73"}}, {"name": "D\u00f3lar CCL", "coti": {"Venta": "$995,20"}}, {"name": "D\u00f3lar mayorista", "coti": {"Venta": "$799,98"}}, {"name": "Euro", "coti": {"Compra": "$855,94", "Venta": "$918,90"}}]}}, {"debug_info": {"running_date": "17/12/23", "running_time": "11:00:06"}, "data": {"coti": [{"name": "D\u00f3lar oficial", "coti": {"Compra": "$782,53", "Venta": "$838,18"}}, {"name": "D\u00f3lar blue", "coti": {"Compra": "$920,00", "Venta": "$970,00"}}, {"name": "D\u00f3lar tarjeta", "coti": {"Venta": "$1341,09"}}, {"name": "D\u00f3lar turista", "coti": {"Venta": "$1341,09"}}, {"name": "D\u00f3lar MEP", "coti": {"Venta": "$1000,73"}}, {"name": "D\u00f3lar CCL", "coti": {"Venta": "$995,20"}}, {"name": "D\u00f3lar mayorista", "coti": {"Venta": "$799,98"}}, {"name": "Euro", "coti": {"Compra": "$855,94", "Venta": "$918,90"}}]}}]